fopen/__init__.py
fopen/util.py
fopen-0.0.4.dist-info/METADATA
fopen-0.0.4.dist-info/WHEEL
fopen-0.0.4.dist-info/licenses/LICENSE
fopen-0.0.4.dist-info/RECORD
