Metadata-Version: 2.1
Name: fopen
Version: 0.0.4
Summary: File parsing shortcut (csv, json, toml, json lines)
Project-URL: Homepage, https://github.com/chemtrails/filetools
Author: Rafał Prażmo
License-File: LICENSE
Classifier: License :: OSI Approved :: MIT License
Classifier: Operating System :: OS Independent
Classifier: Programming Language :: Python :: 3
Requires-Python: >=3.7
